monitering/__init__.py
monitering/check.py
monitering/collect.py
monitering/hello.py
monitering/run.py
tremo/__init__.py
tremo/check.py
tremo/collect.py
tremo/es_module.py
tremo/esmodule.py
tremo/extract.py
tremo/run.py
tremo/tests/__init__.py
tremo/tests/test_check.py
tremo/tests/test_collect.py
tremo/tests/test_connect.py
tremo/tests/test_run.py
tremo-1.0.1.dist-info/LICENSE
tremo-1.0.1.dist-info/METADATA
tremo-1.0.1.dist-info/WHEEL
tremo-1.0.1.dist-info/top_level.txt
tremo-1.0.1.dist-info/RECORD
