Metadata-Version: 2.1
Name: tremo
Version: 1.0.1
Summary: Real-time Trend Data Analysis/Monitoring System
Home-page: https://github.com/thisishoon/trend-monitoring
Author: Jihoon Kang
Author-email: jihoon522@naver.com
License: UNKNOWN
Keywords: trend,tremo,monitoring,analysis,portal,search_word
Platform: UNKNOWN
Classifier: Programming Language :: Python :: 3
Classifier: License :: OSI Approved :: MIT License
Classifier: Operating System :: OS Independent
Requires-Python: >=3
Requires-Dist: bs4
Requires-Dist: konlpy
Requires-Dist: krwordrank
Requires-Dist: elasticsearch
Requires-Dist: newspaper3k
Requires-Dist: requests
